lusid_configuration/__init__.py
lusid_configuration/api/__init__.py
lusid_configuration/api/application_metadata_api.py
lusid_configuration/api/configuration_sets_api.py
lusid_configuration/api_client.py
lusid_configuration/api_response.py
lusid_configuration/configuration.py
lusid_configuration/exceptions.py
lusid_configuration/extensions/__init__.py
lusid_configuration/extensions/api_client.py
lusid_configuration/extensions/api_client_factory.py
lusid_configuration/extensions/api_configuration.py
lusid_configuration/extensions/configuration_loaders.py
lusid_configuration/extensions/configuration_options.py
lusid_configuration/extensions/file_access_token.py
lusid_configuration/extensions/proxy_config.py
lusid_configuration/extensions/refreshing_token.py
lusid_configuration/extensions/rest.py
lusid_configuration/extensions/retry.py
lusid_configuration/extensions/socket_keep_alive.py
lusid_configuration/extensions/tcp_keep_alive_connector.py
lusid_configuration/models/__init__.py
lusid_configuration/models/access_controlled_action.py
lusid_configuration/models/access_controlled_resource.py
lusid_configuration/models/action_id.py
lusid_configuration/models/configuration_item.py
lusid_configuration/models/configuration_item_summary.py
lusid_configuration/models/configuration_set.py
lusid_configuration/models/configuration_set_summary.py
lusid_configuration/models/create_configuration_item.py
lusid_configuration/models/create_configuration_set.py
lusid_configuration/models/id_selector_definition.py
lusid_configuration/models/identifier_part_schema.py
lusid_configuration/models/link.py
lusid_configuration/models/lusid_problem_details.py
lusid_configuration/models/lusid_validation_problem_details.py
lusid_configuration/models/personal_access_token.py
lusid_configuration/models/resource_id.py
lusid_configuration/models/resource_list_of_access_controlled_resource.py
lusid_configuration/models/resource_list_of_configuration_item.py
lusid_configuration_sdk-2.3.1.dist-info/METADATA
lusid_configuration_sdk-2.3.1.dist-info/WHEEL
lusid_configuration_sdk-2.3.1.dist-info/RECORD
