Metadata-Version: 2.4
Name: lusid-configuration-sdk
Version: 2.3.1
Summary: FINBOURNE ConfigurationService API
License: MIT
Keywords: OpenAPI,OpenAPI-Generator,FINBOURNE ConfigurationService API,lusid-configuration-sdk
Author: FINBOURNE Technology
Author-email: info@finbourne.com
Requires-Python: >=3.11,<4.0
Classifier: License :: OSI Approved :: MIT License
Classifier: Programming Language :: Python :: 3
Classifier: Programming Language :: Python :: 3.11
Classifier: Programming Language :: Python :: 3.12
Classifier: Programming Language :: Python :: 3.13
Classifier: Programming Language :: Python :: 3.14
Requires-Dist: aenum (>=3.1.11,<4.0.0)
Requires-Dist: aiohttp (>=3.8.4,<4.0.0)
Requires-Dist: pydantic (>=2.6.3,<3.0.0)
Requires-Dist: python-dateutil (>=2.8.2,<3.0.0)
Requires-Dist: requests (>=2,<3)
Requires-Dist: urllib3 (>=2.6.0,<3.0.0)
Project-URL: Repository, https://github.com/finbourne/configuration-sdk-python
